patronRobertNicuta/__init__.py
patronRobertNicuta/patron_RobertNicuta_expoFP.py
PatronRobertNicuta-0.1.dist-info/METADATA
PatronRobertNicuta-0.1.dist-info/WHEEL
PatronRobertNicuta-0.1.dist-info/top_level.txt
PatronRobertNicuta-0.1.dist-info/RECORD
