Metadata-Version: 2.1
Name: PatronRobertNicuta
Version: 0.1
Summary: Animacion Para Expo 2024 Ibiza
Home-page: https://github.com/robertnic9/patronRobertNicuta
Author: Robert Nicuta
Author-email: robertnicuta80@gmail.com
